tiger_utils/__init__.py
tiger_utils/model.py
tiger_utils/utils.py
tiger_utils-1.0.5.dist-info/METADATA
tiger_utils-1.0.5.dist-info/WHEEL
tiger_utils-1.0.5.dist-info/top_level.txt
tiger_utils-1.0.5.dist-info/RECORD
