Metadata-Version: 2.4
Name: tiger_utils
Version: 1.0.5
Summary: A utility package
Home-page: https://github.com/peterbaile/tiger-utils
Author: peterbc
Author-email: peterbailec@gmail.com
Classifier: Programming Language :: Python :: 3
Classifier: License :: OSI Approved :: MIT License
Classifier: Operating System :: OS Independent
Requires-Python: >=3
Dynamic: author
Dynamic: author-email
Dynamic: classifier
Dynamic: home-page
Dynamic: requires-python
Dynamic: summary
